Metadata-Version: 2.1
Name: fsevector
Version: 1.1.0
Summary: Deepglint fse vectorstore
Home-page: https://gitlab.deepglint.com/chenbo/fsevector
Author: bchen
Author-email: bochen@deepglint.com
License: Apache License 2.0
Project-URL: Documentation, https://gitlab.deepglint.com/chenbo/fsevector
Project-URL: Source, https://gitlab.deepglint.com/chenbo/fsevector
Platform: UNKNOWN
Classifier: Development Status :: 5 - Production/Stable
Classifier: Intended Audience :: Developers
Classifier: Natural Language :: English
Classifier: License :: OSI Approved :: Apache Software License
Classifier: Programming Language :: Python
Classifier: Programming Language :: Python :: 3
Classifier: Programming Language :: Python :: 3.8
Classifier: Programming Language :: Python :: 3.9
Classifier: Programming Language :: Python :: 3.10
Classifier: Programming Language :: Python :: 3.11
Requires-Python: >= 3.8
